webhookguard/__init__.py
webhookguard/errors.py
webhookguard/guard.py
webhookguard-1.0.0.dist-info/METADATA
webhookguard-1.0.0.dist-info/WHEEL
webhookguard-1.0.0.dist-info/licenses/LICENSE
webhookguard-1.0.0.dist-info/RECORD
