Metadata-Version: 2.4
Name: webhookguard
Version: 1.0.0
Summary: A secure webhook signature library for Python.
Project-URL: Homepage, https://github.com/killcod3/webhookguard-python
Project-URL: Bug Tracker, https://github.com/killcod3/webhookguard-python/issues
Author-email: Jawad Shafique <shafiquejr@gmail.com>
License-File: LICENSE
Classifier: License :: OSI Approved :: MIT License
Classifier: Operating System :: OS Independent
Classifier: Programming Language :: Python :: 3
Requires-Python: >=3.7
Requires-Dist: cryptography>=3.4
